etk/__init__.py
etk/__main__.py
etk/black_list_filter.py
etk/cli_entry.py
etk/crf_tokenizer.py
etk/csv_processor.py
etk/doc_retrieve_processor.py
etk/document.py
etk/document_selector.py
etk/etk.py
etk/etk_exceptions.py
etk/etk_module.py
etk/extraction.py
etk/extraction_provenance_record.py
etk/extractor.py
etk/origin_record.py
etk/provenance_api.py
etk/segment.py
etk/simple_timeseries_extractor.py
etk/storage_provenance_record.py
etk/timeseries_processor.py
etk/tokenizer.py
etk/utilities.py
etk/cli/__init__.py
etk/cli/bitcoin_address_extractor.py
etk/cli/cryptographic_hash_extractor.py
etk/cli/cve_extractor.py
etk/cli/date_extractor.py
etk/cli/dummy.py
etk/cli/email_extractor.py
etk/cli/hostname_extractor.py
etk/cli/html_content_extractor.py
etk/cli/html_metadate_extractor.py
etk/cli/ip_address_extractor.py
etk/cli/regex_extractor.py
etk/cli/reonto.py
etk/cli/wd_cleanup.py
etk/cli/wd_update_truthy.py
etk/cli/wd_upload.py
etk/dependencies/__init__.py
etk/dependencies/date_extractor_resources/__init__.py
etk/dependencies/date_extractor_resources/constants.py
etk/dependencies/date_extractor_resources/date_regex_generator.py
etk/dependencies/landmark/__init__.py
etk/dependencies/landmark/setup.py
etk/dependencies/landmark/landmark_extractor/__init__.py
etk/dependencies/landmark/landmark_extractor/extraction/Landmark.py
etk/dependencies/landmark/landmark_extractor/extraction/__init__.py
etk/dependencies/landmark/landmark_extractor/postprocessing/PostProcessor.py
etk/dependencies/landmark/landmark_extractor/postprocessing/__init__.py
etk/dependencies/landmark/landmark_extractor/validation/Validation.py
etk/dependencies/landmark/landmark_extractor/validation/__init__.py
etk/extractors/__init__.py
etk/extractors/bitcoin_address_extractor.py
etk/extractors/cryptographic_hash_extractor.py
etk/extractors/cve_extractor.py
etk/extractors/date_extractor.py
etk/extractors/dbpedia_spotlight_extractor.py
etk/extractors/decoding_value_extractor.py
etk/extractors/email_extractor.py
etk-2.2.8.dist-info/LICENSE.md
etk-2.2.8.dist-info/METADATA
etk-2.2.8.dist-info/WHEEL
etk-2.2.8.dist-info/entry_points.txt
etk-2.2.8.dist-info/top_level.txt
etk-2.2.8.dist-info/RECORD
